pyconfviewer/__init__.py
pyconfviewer/config_generator.py
pyconfviewer/diff_generator.py
pyconfviewer/templates/config_diff_viewer.html
pyconfviewer/templates/config_viewer.html
pyconfviewer-0.1.1.dist-info/LICENSE
pyconfviewer-0.1.1.dist-info/METADATA
pyconfviewer-0.1.1.dist-info/WHEEL
pyconfviewer-0.1.1.dist-info/entry_points.txt
pyconfviewer-0.1.1.dist-info/top_level.txt
pyconfviewer-0.1.1.dist-info/RECORD
