Metadata-Version: 2.1
Name: pyconfviewer
Version: 0.1.1
Summary: A Python library for generating HTML views and diffs for configuration files.
Author-email: pkaiy81 <pkaiy81@outlook.com>
License: MIT
Project-URL: Homepage, https://github.com/pkaiy81/pyconfviewer
Keywords: configuration,HTML,diff,YAML,JSON,env
Classifier: Programming Language :: Python :: 3
Classifier: License :: OSI Approved :: MIT License
Classifier: Operating System :: OS Independent
Requires-Python: >=3.8
License-File: LICENSE
Requires-Dist: pyyaml
Requires-Dist: jsonschema
Requires-Dist: configparser
Requires-Dist: python-dotenv
Requires-Dist: jinja2
Requires-Dist: toml
Provides-Extra: dev
Requires-Dist: pytest>=6.0.0; extra == "dev"
